modelscope/__init__.py
modelscope/metainfo.py
modelscope/pipeline_inputs.py
modelscope/version.py
modelscope/configs/examples/configuration.py
modelscope/exporters/__init__.py
modelscope/exporters/base.py
modelscope/exporters/builder.py
modelscope/exporters/tf_model_exporter.py
modelscope/exporters/torch_model_exporter.py
modelscope/exporters/nlp/__init__.py
modelscope/exporters/nlp/sbert_for_sequence_classification_exporter.py
modelscope/fileio/__init__.py
modelscope/fileio/file.py
modelscope/fileio/io.py
modelscope/fileio/format/__init__.py
modelscope/fileio/format/base.py
modelscope/fileio/format/json.py
modelscope/fileio/format/yaml.py
modelscope/hub/__init__.py
modelscope/hub/api.py
modelscope/hub/check_model.py
modelscope/hub/constants.py
modelscope/hub/deploy.py
modelscope/hub/errors.py
modelscope/hub/file_download.py
modelscope/hub/git.py
modelscope/hub/repository.py
modelscope/hub/snapshot_download.py
modelscope/hub/utils/__init__.py
modelscope/hub/utils/caching.py
modelscope/hub/utils/utils.py
modelscope/metrics/__init__.py
modelscope/metrics/accuracy_metric.py
modelscope/metrics/audio_noise_metric.py
modelscope/metrics/base.py
modelscope/metrics/bleu_metric.py
modelscope/metrics/builder.py
modelscope/metrics/image_color_enhance_metric.py
modelscope/metrics/image_denoise_metric.py
modelscope/metrics/image_inpainting_metric.py
modelscope/metrics/image_instance_segmentation_metric.py
modelscope/metrics/image_portrait_enhancement_metric.py
modelscope/metrics/inbatch_recall_metric.py
modelscope/metrics/map_metric.py
modelscope/metrics/movie_scene_segmentation_metric.py
modelscope/metrics/ned_metric.py
modelscope/metrics/ppl_metric.py
modelscope/metrics/referring_video_object_segmentation_metric.py
modelscope/metrics/sequence_classification_metric.py
modelscope/metrics/text_generation_metric.py
modelscope/metrics/token_classification_metric.py
modelscope/metrics/video_frame_interpolation_metric.py
modelscope/metrics/video_stabilization_metric.py
modelscope-1.2.1.dist-info/METADATA
modelscope-1.2.1.dist-info/WHEEL
modelscope-1.2.1.dist-info/top_level.txt
modelscope-1.2.1.dist-info/RECORD
