Metadata-Version: 2.1
Name: modelscope
Version: 1.2.1
Home-page: https://github.com/modelscope/modelscope
Author: Alibaba ModelScope team
Author-email: modelscope@list.alibaba-inc.com
License: Apache License 2.0
Keywords: python,nlp,science,cv,speech,multi-modal
Classifier: Development Status :: 4 - Beta
Classifier: License :: OSI Approved :: Apache Software License
Classifier: Operating System :: OS Independent
Classifier: Programming Language :: Python :: 3
Classifier: Programming Language :: Python :: 3.7
Classifier: Programming Language :: Python :: 3.8
Classifier: Programming Language :: Python :: 3.9
Classifier: Programming Language :: Python :: 3.10
Requires-Dist: addict
Requires-Dist: attrs
Requires-Dist: datasets (>=2.7.0)
Requires-Dist: easydict
Requires-Dist: einops
Requires-Dist: filelock (>=3.3.0)
Requires-Dist: gast (>=0.2.2)
Requires-Dist: jsonplus
Requires-Dist: numpy
Requires-Dist: oss2
Requires-Dist: Pillow (>=6.2.0)
Requires-Dist: pyarrow (!=9.0.0,>=6.0.0)
Requires-Dist: pyyaml
Requires-Dist: requests
Requires-Dist: scipy
Requires-Dist: setuptools
Requires-Dist: tensorboard
Requires-Dist: tqdm (>=4.64.0)
Requires-Dist: yapf
Provides-Extra: all
Requires-Dist: albumentations (>=1.0.3) ; extra == 'all'
Requires-Dist: av (>=9.2.0) ; extra == 'all'
Requires-Dist: bmt-clipit (>=1.0) ; extra == 'all'
Requires-Dist: clip (>=1.0) ; extra == 'all'
Requires-Dist: easydict ; extra == 'all'
Requires-Dist: easyrobust ; extra == 'all'
Requires-Dist: fairscale (>=0.4.1) ; extra == 'all'
Requires-Dist: fastai (>=1.0.51) ; extra == 'all'
Requires-Dist: ffmpeg (>=1.4) ; extra == 'all'
Requires-Dist: ffmpeg-python (>=0.2.0) ; extra == 'all'
Requires-Dist: ftfy ; extra == 'all'
Requires-Dist: imageio (>=2.9.0) ; extra == 'all'
Requires-Dist: imageio-ffmpeg (>=0.4.2) ; extra == 'all'
Requires-Dist: imgaug (>=0.4.0) ; extra == 'all'
Requires-Dist: kornia (>=0.5.0) ; extra == 'all'
Requires-Dist: lap ; extra == 'all'
Requires-Dist: lmdb ; extra == 'all'
Requires-Dist: lpips ; extra == 'all'
Requires-Dist: ml-collections ; extra == 'all'
Requires-Dist: mmcls (>=0.21.0) ; extra == 'all'
Requires-Dist: mmdet (>=2.25.0) ; extra == 'all'
Requires-Dist: moviepy (>=1.0.3) ; extra == 'all'
Requires-Dist: networkx (>=2.5) ; extra == 'all'
Requires-Dist: numba ; extra == 'all'
Requires-Dist: onnxruntime (>=1.10) ; extra == 'all'
Requires-Dist: opencv-python ; extra == 'all'
Requires-Dist: pai-easycv (>=0.8) ; extra == 'all'
Requires-Dist: pandas ; extra == 'all'
Requires-Dist: panopticapi ; extra == 'all'
Requires-Dist: plyfile (>=0.7.4) ; extra == 'all'
Requires-Dist: psutil ; extra == 'all'
Requires-Dist: regex ; extra == 'all'
Requires-Dist: scikit-image (>=0.19.3) ; extra == 'all'
Requires-Dist: scikit-learn (>=0.20.1) ; extra == 'all'
Requires-Dist: shapely ; extra == 'all'
Requires-Dist: shotdetect-scenedetect-lgss ; extra == 'all'
Requires-Dist: tensorflow-estimator (>=1.15.1) ; extra == 'all'
Requires-Dist: tf-slim ; extra == 'all'
Requires-Dist: timm (>=0.4.9) ; extra == 'all'
Requires-Dist: torchmetrics (>=0.6.2) ; extra == 'all'
Requires-Dist: torchvision ; extra == 'all'
Requires-Dist: ujson ; extra == 'all'
Requires-Dist: utils ; extra == 'all'
Requires-Dist: videofeatures-clipit (>=1.0) ; extra == 'all'
Requires-Dist: accelerate ; extra == 'all'
Requires-Dist: diffusers (>=0.11.1) ; extra == 'all'
Requires-Dist: ftfy (>=6.0.3) ; extra == 'all'
Requires-Dist: librosa ; extra == 'all'
Requires-Dist: pycocoevalcap (>=1.2) ; extra == 'all'
Requires-Dist: pycocotools (>=2.0.4) ; extra == 'all'
Requires-Dist: pytorch-lightning (<=1.7.7) ; extra == 'all'
Requires-Dist: rapidfuzz ; extra == 'all'
Requires-Dist: rouge-score (<=0.0.4) ; extra == 'all'
Requires-Dist: sacrebleu ; extra == 'all'
Requires-Dist: soundfile ; extra == 'all'
Requires-Dist: taming-transformers-rom1504 ; extra == 'all'
Requires-Dist: timm ; extra == 'all'
Requires-Dist: tokenizers ; extra == 'all'
Requires-Dist: transformers (>=4.12.0) ; extra == 'all'
Requires-Dist: unicodedata2 ; extra == 'all'
Requires-Dist: zhconv ; extra == 'all'
Requires-Dist: boto3 ; extra == 'all'
Requires-Dist: en-core-web-sm (>=2.3.5) ; extra == 'all'
Requires-Dist: filelock ; extra == 'all'
Requires-Dist: jieba (>=0.42.1) ; extra == 'all'
Requires-Dist: matplotlib ; extra == 'all'
Requires-Dist: megatron-util ; extra == 'all'
Requires-Dist: nltk ; extra == 'all'
Requires-Dist: protobuf (<3.21.0,>=3.19.0) ; extra == 'all'
Requires-Dist: pythainlp ; extra == 'all'
Requires-Dist: pyvi ; extra == 'all'
Requires-Dist: rouge ; extra == 'all'
Requires-Dist: sacremoses (>=0.0.41) ; extra == 'all'
Requires-Dist: scikit-learn ; extra == 'all'
Requires-Dist: sentencepiece ; extra == 'all'
Requires-Dist: seqeval ; extra == 'all'
Requires-Dist: spacy (>=2.3.5) ; extra == 'all'
Requires-Dist: subword-nmt (>=0.3.8) ; extra == 'all'
Requires-Dist: termcolor ; extra == 'all'
Requires-Dist: text2sql-lgesql ; extra == 'all'
Requires-Dist: biopython ; extra == 'all'
Requires-Dist: iopath ; extra == 'all'
Requires-Dist: ipdb ; extra == 'all'
Requires-Dist: scipy ; extra == 'all'
Requires-Dist: tensorboardX ; extra == 'all'
Provides-Extra: audio
Requires-Dist: easyasr (>=0.0.2) ; extra == 'audio'
Requires-Dist: funasr (>=0.1.7) ; extra == 'audio'
Requires-Dist: kaldiio ; extra == 'audio'
Requires-Dist: kwsbp (>=0.0.2) ; extra == 'audio'
Requires-Dist: matplotlib ; extra == 'audio'
Requires-Dist: numpy ; extra == 'audio'
Requires-Dist: py-sound-connect (>=0.1) ; extra == 'audio'
Requires-Dist: scipy ; extra == 'audio'
Requires-Dist: SoundFile (>0.10) ; extra == 'audio'
Requires-Dist: tensorboardX ; extra == 'audio'
Requires-Dist: hyperpyyaml ; extra == 'audio'
Requires-Dist: librosa ; extra == 'audio'
Requires-Dist: MinDAEC ; extra == 'audio'
Requires-Dist: mir-eval (>=0.7) ; extra == 'audio'
Requires-Dist: rotary-embedding-torch (>=0.1.5) ; extra == 'audio'
Requires-Dist: speechbrain (>=0.5.7) ; extra == 'audio'
Requires-Dist: torchaudio ; extra == 'audio'
Requires-Dist: tqdm ; extra == 'audio'
Requires-Dist: bitstring ; extra == 'audio'
Requires-Dist: greenlet (>=1.1.2) ; extra == 'audio'
Requires-Dist: inflect ; extra == 'audio'
Requires-Dist: jedi (>=0.18.1) ; extra == 'audio'
Requires-Dist: lxml ; extra == 'audio'
Requires-Dist: msgpack (>=1.0.4) ; extra == 'audio'
Requires-Dist: parso (>=0.8.3) ; extra == 'audio'
Requires-Dist: pexpect (>=4.8.0) ; extra == 'audio'
Requires-Dist: pickleshare (>=0.7.5) ; extra == 'audio'
Requires-Dist: prompt-toolkit (>=3.0.30) ; extra == 'audio'
Requires-Dist: protobuf ; extra == 'audio'
Requires-Dist: ptflops ; extra == 'audio'
Requires-Dist: ptyprocess (>=0.7.0) ; extra == 'audio'
Requires-Dist: pygments (>=2.12.0) ; extra == 'audio'
Requires-Dist: pysptk (<0.2.0,>=0.1.15) ; extra == 'audio'
Requires-Dist: pytorch-wavelets ; extra == 'audio'
Requires-Dist: PyWavelets (>=1.0.0) ; extra == 'audio'
Requires-Dist: scikit-learn ; extra == 'audio'
Requires-Dist: sox ; extra == 'audio'
Requires-Dist: traitlets (>=5.3.0) ; extra == 'audio'
Requires-Dist: ttsfrd (>=0.1.1) ; extra == 'audio'
Requires-Dist: unidecode ; extra == 'audio'
Requires-Dist: wcwidth (>=0.2.5) ; extra == 'audio'
Provides-Extra: audio_asr
Requires-Dist: easyasr (>=0.0.2) ; extra == 'audio_asr'
Requires-Dist: funasr (>=0.1.7) ; extra == 'audio_asr'
Provides-Extra: audio_kws
Requires-Dist: kaldiio ; extra == 'audio_kws'
Requires-Dist: kwsbp (>=0.0.2) ; extra == 'audio_kws'
Requires-Dist: matplotlib ; extra == 'audio_kws'
Requires-Dist: numpy ; extra == 'audio_kws'
Requires-Dist: py-sound-connect (>=0.1) ; extra == 'audio_kws'
Requires-Dist: scipy ; extra == 'audio_kws'
Requires-Dist: SoundFile (>0.10) ; extra == 'audio_kws'
Requires-Dist: tensorboardX ; extra == 'audio_kws'
Provides-Extra: audio_signal
Requires-Dist: hyperpyyaml ; extra == 'audio_signal'
Requires-Dist: librosa ; extra == 'audio_signal'
Requires-Dist: MinDAEC ; extra == 'audio_signal'
Requires-Dist: mir-eval (>=0.7) ; extra == 'audio_signal'
Requires-Dist: numpy ; extra == 'audio_signal'
Requires-Dist: rotary-embedding-torch (>=0.1.5) ; extra == 'audio_signal'
Requires-Dist: scipy ; extra == 'audio_signal'
Requires-Dist: SoundFile (>0.10) ; extra == 'audio_signal'
Requires-Dist: speechbrain (>=0.5.7) ; extra == 'audio_signal'
Requires-Dist: torchaudio ; extra == 'audio_signal'
Requires-Dist: tqdm ; extra == 'audio_signal'
Provides-Extra: audio_tts
Requires-Dist: bitstring ; extra == 'audio_tts'
Requires-Dist: greenlet (>=1.1.2) ; extra == 'audio_tts'
Requires-Dist: inflect ; extra == 'audio_tts'
Requires-Dist: jedi (>=0.18.1) ; extra == 'audio_tts'
Requires-Dist: librosa ; extra == 'audio_tts'
Requires-Dist: lxml ; extra == 'audio_tts'
Requires-Dist: matplotlib ; extra == 'audio_tts'
Requires-Dist: msgpack (>=1.0.4) ; extra == 'audio_tts'
Requires-Dist: parso (>=0.8.3) ; extra == 'audio_tts'
Requires-Dist: pexpect (>=4.8.0) ; extra == 'audio_tts'
Requires-Dist: pickleshare (>=0.7.5) ; extra == 'audio_tts'
Requires-Dist: prompt-toolkit (>=3.0.30) ; extra == 'audio_tts'
Requires-Dist: protobuf ; extra == 'audio_tts'
Requires-Dist: ptflops ; extra == 'audio_tts'
Requires-Dist: ptyprocess (>=0.7.0) ; extra == 'audio_tts'
Requires-Dist: pygments (>=2.12.0) ; extra == 'audio_tts'
Requires-Dist: pysptk (<0.2.0,>=0.1.15) ; extra == 'audio_tts'
Requires-Dist: pytorch-wavelets ; extra == 'audio_tts'
Requires-Dist: PyWavelets (>=1.0.0) ; extra == 'audio_tts'
Requires-Dist: scikit-learn ; extra == 'audio_tts'
Requires-Dist: sox ; extra == 'audio_tts'
Requires-Dist: tensorboardx ; extra == 'audio_tts'
Requires-Dist: tqdm ; extra == 'audio_tts'
Requires-Dist: traitlets (>=5.3.0) ; extra == 'audio_tts'
Requires-Dist: ttsfrd (>=0.1.1) ; extra == 'audio_tts'
Requires-Dist: unidecode ; extra == 'audio_tts'
Requires-Dist: wcwidth (>=0.2.5) ; extra == 'audio_tts'
Provides-Extra: cv
Requires-Dist: albumentations (>=1.0.3) ; extra == 'cv'
Requires-Dist: av (>=9.2.0) ; extra == 'cv'
Requires-Dist: bmt-clipit (>=1.0) ; extra == 'cv'
Requires-Dist: clip (>=1.0) ; extra == 'cv'
Requires-Dist: easydict ; extra == 'cv'
Requires-Dist: easyrobust ; extra == 'cv'
Requires-Dist: fairscale (>=0.4.1) ; extra == 'cv'
Requires-Dist: fastai (>=1.0.51) ; extra == 'cv'
Requires-Dist: ffmpeg (>=1.4) ; extra == 'cv'
Requires-Dist: ffmpeg-python (>=0.2.0) ; extra == 'cv'
Requires-Dist: ftfy ; extra == 'cv'
Requires-Dist: imageio (>=2.9.0) ; extra == 'cv'
Requires-Dist: imageio-ffmpeg (>=0.4.2) ; extra == 'cv'
Requires-Dist: imgaug (>=0.4.0) ; extra == 'cv'
Requires-Dist: kornia (>=0.5.0) ; extra == 'cv'
Requires-Dist: lap ; extra == 'cv'
Requires-Dist: lmdb ; extra == 'cv'
Requires-Dist: lpips ; extra == 'cv'
Requires-Dist: ml-collections ; extra == 'cv'
Requires-Dist: mmcls (>=0.21.0) ; extra == 'cv'
Requires-Dist: mmdet (>=2.25.0) ; extra == 'cv'
Requires-Dist: moviepy (>=1.0.3) ; extra == 'cv'
Requires-Dist: networkx (>=2.5) ; extra == 'cv'
Requires-Dist: numba ; extra == 'cv'
Requires-Dist: onnxruntime (>=1.10) ; extra == 'cv'
Requires-Dist: opencv-python ; extra == 'cv'
Requires-Dist: pai-easycv (>=0.8) ; extra == 'cv'
Requires-Dist: pandas ; extra == 'cv'
Requires-Dist: panopticapi ; extra == 'cv'
Requires-Dist: plyfile (>=0.7.4) ; extra == 'cv'
Requires-Dist: psutil ; extra == 'cv'
Requires-Dist: regex ; extra == 'cv'
Requires-Dist: scikit-image (>=0.19.3) ; extra == 'cv'
Requires-Dist: scikit-learn (>=0.20.1) ; extra == 'cv'
Requires-Dist: shapely ; extra == 'cv'
Requires-Dist: shotdetect-scenedetect-lgss ; extra == 'cv'
Requires-Dist: tensorflow-estimator (>=1.15.1) ; extra == 'cv'
Requires-Dist: tf-slim ; extra == 'cv'
Requires-Dist: timm (>=0.4.9) ; extra == 'cv'
Requires-Dist: torchmetrics (>=0.6.2) ; extra == 'cv'
Requires-Dist: torchvision ; extra == 'cv'
Requires-Dist: ujson ; extra == 'cv'
Requires-Dist: utils ; extra == 'cv'
Requires-Dist: videofeatures-clipit (>=1.0) ; extra == 'cv'
Provides-Extra: multi-modal
Requires-Dist: accelerate ; extra == 'multi-modal'
Requires-Dist: diffusers (>=0.11.1) ; extra == 'multi-modal'
Requires-Dist: ftfy (>=6.0.3) ; extra == 'multi-modal'
Requires-Dist: librosa ; extra == 'multi-modal'
Requires-Dist: opencv-python ; extra == 'multi-modal'
Requires-Dist: pycocoevalcap (>=1.2) ; extra == 'multi-modal'
Requires-Dist: pycocotools (>=2.0.4) ; extra == 'multi-modal'
Requires-Dist: pytorch-lightning (<=1.7.7) ; extra == 'multi-modal'
Requires-Dist: rapidfuzz ; extra == 'multi-modal'
Requires-Dist: rouge-score (<=0.0.4) ; extra == 'multi-modal'
Requires-Dist: sacrebleu ; extra == 'multi-modal'
Requires-Dist: soundfile ; extra == 'multi-modal'
Requires-Dist: taming-transformers-rom1504 ; extra == 'multi-modal'
Requires-Dist: timm ; extra == 'multi-modal'
Requires-Dist: tokenizers ; extra == 'multi-modal'
Requires-Dist: torchvision ; extra == 'multi-modal'
Requires-Dist: transformers (>=4.12.0) ; extra == 'multi-modal'
Requires-Dist: unicodedata2 ; extra == 'multi-modal'
Requires-Dist: zhconv ; extra == 'multi-modal'
Provides-Extra: nlp
Requires-Dist: boto3 ; extra == 'nlp'
Requires-Dist: en-core-web-sm (>=2.3.5) ; extra == 'nlp'
Requires-Dist: filelock ; extra == 'nlp'
Requires-Dist: ftfy ; extra == 'nlp'
Requires-Dist: jieba (>=0.42.1) ; extra == 'nlp'
Requires-Dist: matplotlib ; extra == 'nlp'
Requires-Dist: megatron-util ; extra == 'nlp'
Requires-Dist: nltk ; extra == 'nlp'
Requires-Dist: pandas ; extra == 'nlp'
Requires-Dist: protobuf (<3.21.0,>=3.19.0) ; extra == 'nlp'
Requires-Dist: pythainlp ; extra == 'nlp'
Requires-Dist: pyvi ; extra == 'nlp'
Requires-Dist: regex ; extra == 'nlp'
Requires-Dist: rouge ; extra == 'nlp'
Requires-Dist: sacremoses (>=0.0.41) ; extra == 'nlp'
Requires-Dist: scikit-learn ; extra == 'nlp'
Requires-Dist: sentencepiece ; extra == 'nlp'
Requires-Dist: seqeval ; extra == 'nlp'
Requires-Dist: spacy (>=2.3.5) ; extra == 'nlp'
Requires-Dist: subword-nmt (>=0.3.8) ; extra == 'nlp'
Requires-Dist: termcolor ; extra == 'nlp'
Requires-Dist: text2sql-lgesql ; extra == 'nlp'
Requires-Dist: tokenizers ; extra == 'nlp'
Requires-Dist: transformers (>=4.12.0) ; extra == 'nlp'
Provides-Extra: science
Requires-Dist: biopython ; extra == 'science'
Requires-Dist: iopath ; extra == 'science'
Requires-Dist: ipdb ; extra == 'science'
Requires-Dist: lmdb ; extra == 'science'
Requires-Dist: ml-collections ; extra == 'science'
Requires-Dist: scipy ; extra == 'science'
Requires-Dist: tensorboardX ; extra == 'science'
Requires-Dist: tokenizers ; extra == 'science'
